setup.py
acl_library/__init__.py
acl_library/admin.py
acl_library/apps.py
acl_library/models.py
acl_library/schemas.py
acl_library/serializers.py
acl_library/tests.py
acl_library/urls.py
acl_library/views.py
acl_library.egg-info/PKG-INFO
acl_library.egg-info/SOURCES.txt
acl_library.egg-info/dependency_links.txt
acl_library.egg-info/requires.txt
acl_library.egg-info/top_level.txt
acl_library/migrations/0001_initial.py
acl_library/migrations/0002_remove_group_created_at_remove_group_created_by_and_more.py
acl_library/migrations/__init__.py
acl_permissions/__init__.py
acl_permissions/asgi.py
acl_permissions/settings.py
acl_permissions/urls.py
acl_permissions/utils.py
acl_permissions/wsgi.py